Workbook

Sheet Inputs
A1: Susa pricing model: change the yellow cells. Tag: S = sourced from research, A = assumption you must replace with a quote or measurement.
A2: Item | B2: Value | C2: Tag | D2: Note / source
A3: Vehicle loan amount (R) | B3: 150000 | C3: S | D3: Owner brief
A4: Interest rate per year | B4: 0.11 | C4: S | D4: Owner brief. Prime is 10.75% from 25 Sep 2026
A5: Loan term (months) | B5: 72 | C5: S | D5: Owner brief
A6: Initiation fee (R) | B6: 1207.5 | C6: S | D6: NCA maximum, bank fee schedule 2026
A7: Monthly service fee (R) | B7: 69 | C7: S | D7: Bank fee schedule 2026
A8: Trailer cost (R) | B8: 50000 | C8: A | D8: Not researched. Get a quote for a closed braked box trailer
A9: Trailer write-off period (months) | B9: 72 | C9: A
A10: Insurance per month (R) vehicle + trailer + liability | B10: 1700 | C10: A | D10: Get 3 commercial quotes (Miway, King Price, others). Say it is a removals business
A11: Tracker per month (R) | B11: 180 | C11: A
A12: Licence, disc and roadworthy per year (R) | B12: 1200 | C12: S | D12: Typical range R600 to R1,200 a year
A13: Phone and data per month (R) | B13: 400 | C13: A
A14: Accounting per month (R) | B14: 500 | C14: A
A15: Bank fees per month (R) | B15: 150 | C15: A
A16: Marketing per month (R) | B16: 1500 | C16: A | D16: Google Ads, flyers
A17: Misc and domain per month (R) | B17: 150 | C17: A
A18: Equipment (blankets, straps, trolley) total (R) | B18: 3000 | C18: A | D18: Written off over 36 months
A19: Diesel pump price (R per litre) | B19: 33.5 | C19: S/A | D19: Wholesale 500ppm R31.95 from 7 Oct 2026; pump price is an estimate. Update monthly
A20: Fuel use bakkie alone (L per 100 km) | B20: 11.5 | C20: S/A | D20: Maker figure 10.2; loaded real-world estimate
A21: Fuel use bakkie + trailer (L per 100 km) | B21: 13.5 | C21: A
A22: Maintenance, tyres, repairs bakkie (R per km) | B22: 1.3 | C22: A | D22: Tyres about R2,000 each per 50,000 km, services every 15,000 km
A23: Maintenance, tyres, repairs with trailer (R per km) | B23: 1.6 | C23: A
A24: Driven km per move km (positioning factor) | B24: 1.6 | C24: A | D24: Depot to pick-up and back
A25: Extra driven km per job | B25: 8 | C25: A
A26: Average speed in traffic (km per h) | B26: 30 | C26: A
A27: National minimum wage (R per h) | B27: 30.23 | C27: S | D27: From 1 March 2026
A28: Mover wage you pay (R per h) | B28: 35 | C28: A | D28: Must be at least the minimum wage
A29: Driver wage or value of your own time (R per h) | B29: 50 | C29: A
A30: Sunday pay multiplier | B30: 1.5 | C30: S/A | D30: BCEA s16: double, or 1.5 if Sunday is an ordinary working day. Confirm
A31: Employer on-costs (UIF 1% + COIDA 2.65%) | B31: 0.0365 | C31: S/A | D31: COIDA class J goods transport is an assumption. Confirm with the Compensation Fund
A32: Minimum paid hours per mover per job | B32: 4 | C32: A
A33: Breakage and claims provision (share of revenue) | B33: 0.02 | C33: A | D33: You have no goods-in-transit insurance
A34: Target profit margin on price | B34: 0.2 | C34: A

Sheet Monthly costs
A1: Fixed monthly costs | B1: R per month | C1: How
A2: Vehicle instalment | B2: =PMT(Inputs!$B$4/12,Inputs!$B$5,-Inputs!$B$3) -> 2855.1119 | C2: PMT on the loan
A3: Monthly service fee | B3: =Inputs!$B$7 -> 69
A4: Initiation fee spread | B4: =Inputs!$B$6/Inputs!$B$5 -> 16.770833
A5: Trailer write-off | B5: =Inputs!$B$8/Inputs!$B$9 -> 694.44444
A6: Insurance | B6: =Inputs!$B$10 -> 1700
A7: Tracker | B7: =Inputs!$B$11 -> 180
A8: Licence and roadworthy | B8: =Inputs!$B$12/12 -> 100
A9: Phone and data | B9: =Inputs!$B$13 -> 400
A10: Accounting | B10: =Inputs!$B$14 -> 500
A11: Bank fees | B11: =Inputs!$B$15 -> 150
A12: Marketing | B12: =Inputs!$B$16 -> 1500
A13: Misc and domain | B13: =Inputs!$B$17 -> 150
A14: Equipment | B14: =Inputs!$B$18/36 -> 83.333333
A15: TOTAL fixed per month | B15: =SUM(B2:B14) -> 8398.6605
A16: Total fixed excluding trailer (bakkie-only jobs) | B16: =B15-B5 -> 7704.216
A18: Total interest over the loan | B18: =B2*Inputs!$B$5-Inputs!$B$3 -> 55568.053
A19: Running cost per km, bakkie alone | B19: =Inputs!$B$20*Inputs!$B$19/100+Inputs!$B$22 -> 5.1525
A20: Running cost per km, bakkie + trailer | B20: =Inputs!$B$21*Inputs!$B$19/100+Inputs!$B$23 -> 6.1225
A21: Mover cost per paid hour (Sunday, with on-costs) | B21: =Inputs!$B$28*Inputs!$B$30*(1+Inputs!$B$31) -> 54.41625
A22: Driver cost per paid hour (Sunday, with on-costs) | B22: =Inputs!$B$29*Inputs!$B$30*(1+Inputs!$B$31) -> 77.7375
A23: Minimum wage check (mover wage minus minimum) | B23: =Inputs!$B$28-Inputs!$B$27 -> 4.77 | C23: must be 0 or more

Sheet Job costs
A1: Example jobs (yellow = change) | B1: Combo? (1 = with trailer) | C1: Volume m3 | D1: Move km | E1: Floors | F1: Movers (max 2)
A2: T1 bakkie transport only, student | B2: 0 | C2: 1.7 | D2: 10 | E2: 0 | F2: 0
A3: T2 bakkie + 2 movers, student room | B3: 0 | C3: 1.7 | D3: 10 | E3: 0 | F3: 2
A4: T3 combo + 2 movers, 1-bedroom | B4: 1 | C4: 4.7 | D4: 20 | E4: 2 | F4: 2
A5: T4 combo transport only | B5: 1 | C5: 3 | D5: 25 | E5: 0 | F5: 0
A6: T5 combo + 2 movers, 2-bedroom | B6: 1 | C6: 6 | D6: 30 | E6: 3 | F6: 2
A8: At 8 jobs per month
A9: Job | B9: Hours | C9: Driven km | D9: Running cost R | E9: Labour R | F9: Fixed share R | G9: Full cost R | H9: Break-even price R | I9: Price for target margin R
A10: =A2 -> T1 bakkie transport only, student | B10: =MAX(2,CEILING((0.5+0.4*C2+0.25*E2+C10/Inputs!$B$26)*2,1)/2) -> 2 | C10: =Inputs!$B$24*D2+Inputs!$B$25 -> 24 | D10: =C10*IF(B2=1,'Monthly costs'!$B$20,'Monthly costs'!$B$19) -> 123.66 | E10: =MAX(B10,IF(F2>0,Inputs!$B$32,3))*('Monthly costs'!$B$22+F2*'Monthly costs'!$B$21) -> 233.2125 | F10: =IF(B2=1,'Monthly costs'!$B$15,'Monthly costs'!$B$16)/8 -> 963.027 | G10: =D10+E10+F10 -> 1319.8995 | H10: =G10/(1-Inputs!$B$33) -> 1346.8362 | I10: =G10/(1-Inputs!$B$33-Inputs!$B$34) -> 1692.1788
A11: =A3 -> T2 bakkie + 2 movers, student room | B11: =MAX(2,CEILING((0.5+0.4*C3+0.25*E3+C11/Inputs!$B$26)*2,1)/2) -> 2 | C11: =Inputs!$B$24*D3+Inputs!$B$25 -> 24 | D11: =C11*IF(B3=1,'Monthly costs'!$B$20,'Monthly costs'!$B$19) -> 123.66 | E11: =MAX(B11,IF(F3>0,Inputs!$B$32,3))*('Monthly costs'!$B$22+F3*'Monthly costs'!$B$21) -> 746.28 | F11: =IF(B3=1,'Monthly costs'!$B$15,'Monthly costs'!$B$16)/8 -> 963.027 | G11: =D11+E11+F11 -> 1832.967 | H11: =G11/(1-Inputs!$B$33) -> 1870.3745 | I11: =G11/(1-Inputs!$B$33-Inputs!$B$34) -> 2349.9577
A12: =A4 -> T3 combo + 2 movers, 1-bedroom | B12: =MAX(2,CEILING((0.5+0.4*C4+0.25*E4+C12/Inputs!$B$26)*2,1)/2) -> 4.5 | C12: =Inputs!$B$24*D4+Inputs!$B$25 -> 40 | D12: =C12*IF(B4=1,'Monthly costs'!$B$20,'Monthly costs'!$B$19) -> 244.9 | E12: =MAX(B12,IF(F4>0,Inputs!$B$32,3))*('Monthly costs'!$B$22+F4*'Monthly costs'!$B$21) -> 839.565 | F12: =IF(B4=1,'Monthly costs'!$B$15,'Monthly costs'!$B$16)/8 -> 1049.8326 | G12: =D12+E12+F12 -> 2134.2976 | H12: =G12/(1-Inputs!$B$33) -> 2177.8547 | I12: =G12/(1-Inputs!$B$33-Inputs!$B$34) -> 2736.2789
A13: =A5 -> T4 combo transport only | B13: =MAX(2,CEILING((0.5+0.4*C5+0.25*E5+C13/Inputs!$B$26)*2,1)/2) -> 3.5 | C13: =Inputs!$B$24*D5+Inputs!$B$25 -> 48 | D13: =C13*IF(B5=1,'Monthly costs'!$B$20,'Monthly costs'!$B$19) -> 293.88 | E13: =MAX(B13,IF(F5>0,Inputs!$B$32,3))*('Monthly costs'!$B$22+F5*'Monthly costs'!$B$21) -> 272.08125 | F13: =IF(B5=1,'Monthly costs'!$B$15,'Monthly costs'!$B$16)/8 -> 1049.8326 | G13: =D13+E13+F13 -> 1615.7938 | H13: =G13/(1-Inputs!$B$33) -> 1648.7692 | I13: =G13/(1-Inputs!$B$33-Inputs!$B$34) -> 2071.5305
A14: =A6 -> T5 combo + 2 movers, 2-bedroom | B14: =MAX(2,CEILING((0.5+0.4*C6+0.25*E6+C14/Inputs!$B$26)*2,1)/2) -> 6 | C14: =Inputs!$B$24*D6+Inputs!$B$25 -> 56 | D14: =C14*IF(B6=1,'Monthly costs'!$B$20,'Monthly costs'!$B$19) -> 342.86 | E14: =MAX(B14,IF(F6>0,Inputs!$B$32,3))*('Monthly costs'!$B$22+F6*'Monthly costs'!$B$21) -> 1119.42 | F14: =IF(B6=1,'Monthly costs'!$B$15,'Monthly costs'!$B$16)/8 -> 1049.8326 | G14: =D14+E14+F14 -> 2512.1126 | H14: =G14/(1-Inputs!$B$33) -> 2563.3802 | I14: =G14/(1-Inputs!$B$33-Inputs!$B$34) -> 3220.6571
A16: At 12 jobs per month
A17: Job | B17: Hours | C17: Driven km | D17: Running cost R | E17: Labour R | F17: Fixed share R | G17: Full cost R | H17: Break-even price R | I17: Price for target margin R
A18: =A2 -> T1 bakkie transport only, student | B18: =MAX(2,CEILING((0.5+0.4*C2+0.25*E2+C18/Inputs!$B$26)*2,1)/2) -> 2 | C18: =Inputs!$B$24*D2+Inputs!$B$25 -> 24 | D18: =C18*IF(B2=1,'Monthly costs'!$B$20,'Monthly costs'!$B$19) -> 123.66 | E18: =MAX(B18,IF(F2>0,Inputs!$B$32,3))*('Monthly costs'!$B$22+F2*'Monthly costs'!$B$21) -> 233.2125 | F18: =IF(B2=1,'Monthly costs'!$B$15,'Monthly costs'!$B$16)/12 -> 642.018 | G18: =D18+E18+F18 -> 998.8905 | H18: =G18/(1-Inputs!$B$33) -> 1019.276 | I18: =G18/(1-Inputs!$B$33-Inputs!$B$34) -> 1280.6288
A19: =A3 -> T2 bakkie + 2 movers, student room | B19: =MAX(2,CEILING((0.5+0.4*C3+0.25*E3+C19/Inputs!$B$26)*2,1)/2) -> 2 | C19: =Inputs!$B$24*D3+Inputs!$B$25 -> 24 | D19: =C19*IF(B3=1,'Monthly costs'!$B$20,'Monthly costs'!$B$19) -> 123.66 | E19: =MAX(B19,IF(F3>0,Inputs!$B$32,3))*('Monthly costs'!$B$22+F3*'Monthly costs'!$B$21) -> 746.28 | F19: =IF(B3=1,'Monthly costs'!$B$15,'Monthly costs'!$B$16)/12 -> 642.018 | G19: =D19+E19+F19 -> 1511.958 | H19: =G19/(1-Inputs!$B$33) -> 1542.8143 | I19: =G19/(1-Inputs!$B$33-Inputs!$B$34) -> 1938.4077
A20: =A4 -> T3 combo + 2 movers, 1-bedroom | B20: =MAX(2,CEILING((0.5+0.4*C4+0.25*E4+C20/Inputs!$B$26)*2,1)/2) -> 4.5 | C20: =Inputs!$B$24*D4+Inputs!$B$25 -> 40 | D20: =C20*IF(B4=1,'Monthly costs'!$B$20,'Monthly costs'!$B$19) -> 244.9 | E20: =MAX(B20,IF(F4>0,Inputs!$B$32,3))*('Monthly costs'!$B$22+F4*'Monthly costs'!$B$21) -> 839.565 | F20: =IF(B4=1,'Monthly costs'!$B$15,'Monthly costs'!$B$16)/12 -> 699.88837 | G20: =D20+E20+F20 -> 1784.3534 | H20: =G20/(1-Inputs!$B$33) -> 1820.7687 | I20: =G20/(1-Inputs!$B$33-Inputs!$B$34) -> 2287.6325
A21: =A5 -> T4 combo transport only | B21: =MAX(2,CEILING((0.5+0.4*C5+0.25*E5+C21/Inputs!$B$26)*2,1)/2) -> 3.5 | C21: =Inputs!$B$24*D5+Inputs!$B$25 -> 48 | D21: =C21*IF(B5=1,'Monthly costs'!$B$20,'Monthly costs'!$B$19) -> 293.88 | E21: =MAX(B21,IF(F5>0,Inputs!$B$32,3))*('Monthly costs'!$B$22+F5*'Monthly costs'!$B$21) -> 272.08125 | F21: =IF(B5=1,'Monthly costs'!$B$15,'Monthly costs'!$B$16)/12 -> 699.88837 | G21: =D21+E21+F21 -> 1265.8496 | H21: =G21/(1-Inputs!$B$33) -> 1291.6833 | I21: =G21/(1-Inputs!$B$33-Inputs!$B$34) -> 1622.8841
A22: =A6 -> T5 combo + 2 movers, 2-bedroom | B22: =MAX(2,CEILING((0.5+0.4*C6+0.25*E6+C22/Inputs!$B$26)*2,1)/2) -> 6 | C22: =Inputs!$B$24*D6+Inputs!$B$25 -> 56 | D22: =C22*IF(B6=1,'Monthly costs'!$B$20,'Monthly costs'!$B$19) -> 342.86 | E22: =MAX(B22,IF(F6>0,Inputs!$B$32,3))*('Monthly costs'!$B$22+F6*'Monthly costs'!$B$21) -> 1119.42 | F22: =IF(B6=1,'Monthly costs'!$B$15,'Monthly costs'!$B$16)/12 -> 699.88837 | G22: =D22+E22+F22 -> 2162.1684 | H22: =G22/(1-Inputs!$B$33) -> 2206.2943 | I22: =G22/(1-Inputs!$B$33-Inputs!$B$34) -> 2772.0107
A24: At 16 jobs per month
A25: Job | B25: Hours | C25: Driven km | D25: Running cost R | E25: Labour R | F25: Fixed share R | G25: Full cost R | H25: Break-even price R | I25: Price for target margin R
A26: =A2 -> T1 bakkie transport only, student | B26: =MAX(2,CEILING((0.5+0.4*C2+0.25*E2+C26/Inputs!$B$26)*2,1)/2) -> 2 | C26: =Inputs!$B$24*D2+Inputs!$B$25 -> 24 | D26: =C26*IF(B2=1,'Monthly costs'!$B$20,'Monthly costs'!$B$19) -> 123.66 | E26: =MAX(B26,IF(F2>0,Inputs!$B$32,3))*('Monthly costs'!$B$22+F2*'Monthly costs'!$B$21) -> 233.2125 | F26: =IF(B2=1,'Monthly costs'!$B$15,'Monthly costs'!$B$16)/16 -> 481.5135 | G26: =D26+E26+F26 -> 838.386 | H26: =G26/(1-Inputs!$B$33) -> 855.49592 | I26: =G26/(1-Inputs!$B$33-Inputs!$B$34) -> 1074.8538
A27: =A3 -> T2 bakkie + 2 movers, student room | B27: =MAX(2,CEILING((0.5+0.4*C3+0.25*E3+C27/Inputs!$B$26)*2,1)/2) -> 2 | C27: =Inputs!$B$24*D3+Inputs!$B$25 -> 24 | D27: =C27*IF(B3=1,'Monthly costs'!$B$20,'Monthly costs'!$B$19) -> 123.66 | E27: =MAX(B27,IF(F3>0,Inputs!$B$32,3))*('Monthly costs'!$B$22+F3*'Monthly costs'!$B$21) -> 746.28 | F27: =IF(B3=1,'Monthly costs'!$B$15,'Monthly costs'!$B$16)/16 -> 481.5135 | G27: =D27+E27+F27 -> 1351.4535 | H27: =G27/(1-Inputs!$B$33) -> 1379.0342 | I27: =G27/(1-Inputs!$B$33-Inputs!$B$34) -> 1732.6327
A28: =A4 -> T3 combo + 2 movers, 1-bedroom | B28: =MAX(2,CEILING((0.5+0.4*C4+0.25*E4+C28/Inputs!$B$26)*2,1)/2) -> 4.5 | C28: =Inputs!$B$24*D4+Inputs!$B$25 -> 40 | D28: =C28*IF(B4=1,'Monthly costs'!$B$20,'Monthly costs'!$B$19) -> 244.9 | E28: =MAX(B28,IF(F4>0,Inputs!$B$32,3))*('Monthly costs'!$B$22+F4*'Monthly costs'!$B$21) -> 839.565 | F28: =IF(B4=1,'Monthly costs'!$B$15,'Monthly costs'!$B$16)/16 -> 524.91628 | G28: =D28+E28+F28 -> 1609.3813 | H28: =G28/(1-Inputs!$B$33) -> 1642.2258 | I28: =G28/(1-Inputs!$B$33-Inputs!$B$34) -> 2063.3093
A29: =A5 -> T4 combo transport only | B29: =MAX(2,CEILING((0.5+0.4*C5+0.25*E5+C29/Inputs!$B$26)*2,1)/2) -> 3.5 | C29: =Inputs!$B$24*D5+Inputs!$B$25 -> 48 | D29: =C29*IF(B5=1,'Monthly costs'!$B$20,'Monthly costs'!$B$19) -> 293.88 | E29: =MAX(B29,IF(F5>0,Inputs!$B$32,3))*('Monthly costs'!$B$22+F5*'Monthly costs'!$B$21) -> 272.08125 | F29: =IF(B5=1,'Monthly costs'!$B$15,'Monthly costs'!$B$16)/16 -> 524.91628 | G29: =D29+E29+F29 -> 1090.8775 | H29: =G29/(1-Inputs!$B$33) -> 1113.1403 | I29: =G29/(1-Inputs!$B$33-Inputs!$B$34) -> 1398.5609
A30: =A6 -> T5 combo + 2 movers, 2-bedroom | B30: =MAX(2,CEILING((0.5+0.4*C6+0.25*E6+C30/Inputs!$B$26)*2,1)/2) -> 6 | C30: =Inputs!$B$24*D6+Inputs!$B$25 -> 56 | D30: =C30*IF(B6=1,'Monthly costs'!$B$20,'Monthly costs'!$B$19) -> 342.86 | E30: =MAX(B30,IF(F6>0,Inputs!$B$32,3))*('Monthly costs'!$B$22+F6*'Monthly costs'!$B$21) -> 1119.42 | F30: =IF(B6=1,'Monthly costs'!$B$15,'Monthly costs'!$B$16)/16 -> 524.91628 | G30: =D30+E30+F30 -> 1987.1963 | H30: =G30/(1-Inputs!$B$33) -> 2027.7513 | I30: =G30/(1-Inputs!$B$33-Inputs!$B$34) -> 2547.6875
A32: At 20 jobs per month
A33: Job | B33: Hours | C33: Driven km | D33: Running cost R | E33: Labour R | F33: Fixed share R | G33: Full cost R | H33: Break-even price R | I33: Price for target margin R
A34: =A2 -> T1 bakkie transport only, student | B34: =MAX(2,CEILING((0.5+0.4*C2+0.25*E2+C34/Inputs!$B$26)*2,1)/2) -> 2 | C34: =Inputs!$B$24*D2+Inputs!$B$25 -> 24 | D34: =C34*IF(B2=1,'Monthly costs'!$B$20,'Monthly costs'!$B$19) -> 123.66 | E34: =MAX(B34,IF(F2>0,Inputs!$B$32,3))*('Monthly costs'!$B$22+F2*'Monthly costs'!$B$21) -> 233.2125 | F34: =IF(B2=1,'Monthly costs'!$B$15,'Monthly costs'!$B$16)/20 -> 385.2108 | G34: =D34+E34+F34 -> 742.0833 | H34: =G34/(1-Inputs!$B$33) -> 757.22786 | I34: =G34/(1-Inputs!$B$33-Inputs!$B$34) -> 951.38885
A35: =A3 -> T2 bakkie + 2 movers, student room | B35: =MAX(2,CEILING((0.5+0.4*C3+0.25*E3+C35/Inputs!$B$26)*2,1)/2) -> 2 | C35: =Inputs!$B$24*D3+Inputs!$B$25 -> 24 | D35: =C35*IF(B3=1,'Monthly costs'!$B$20,'Monthly costs'!$B$19) -> 123.66 | E35: =MAX(B35,IF(F3>0,Inputs!$B$32,3))*('Monthly costs'!$B$22+F3*'Monthly costs'!$B$21) -> 746.28 | F35: =IF(B3=1,'Monthly costs'!$B$15,'Monthly costs'!$B$16)/20 -> 385.2108 | G35: =D35+E35+F35 -> 1255.1508 | H35: =G35/(1-Inputs!$B$33) -> 1280.7661 | I35: =G35/(1-Inputs!$B$33-Inputs!$B$34) -> 1609.1677
A36: =A4 -> T3 combo + 2 movers, 1-bedroom | B36: =MAX(2,CEILING((0.5+0.4*C4+0.25*E4+C36/Inputs!$B$26)*2,1)/2) -> 4.5 | C36: =Inputs!$B$24*D4+Inputs!$B$25 -> 40 | D36: =C36*IF(B4=1,'Monthly costs'!$B$20,'Monthly costs'!$B$19) -> 244.9 | E36: =MAX(B36,IF(F4>0,Inputs!$B$32,3))*('Monthly costs'!$B$22+F4*'Monthly costs'!$B$21) -> 839.565 | F36: =IF(B4=1,'Monthly costs'!$B$15,'Monthly costs'!$B$16)/20 -> 419.93302 | G36: =D36+E36+F36 -> 1504.398 | H36: =G36/(1-Inputs!$B$33) -> 1535.1 | I36: =G36/(1-Inputs!$B$33-Inputs!$B$34) -> 1928.7154
A37: =A5 -> T4 combo transport only | B37: =MAX(2,CEILING((0.5+0.4*C5+0.25*E5+C37/Inputs!$B$26)*2,1)/2) -> 3.5 | C37: =Inputs!$B$24*D5+Inputs!$B$25 -> 48 | D37: =C37*IF(B5=1,'Monthly costs'!$B$20,'Monthly costs'!$B$19) -> 293.88 | E37: =MAX(B37,IF(F5>0,Inputs!$B$32,3))*('Monthly costs'!$B$22+F5*'Monthly costs'!$B$21) -> 272.08125 | F37: =IF(B5=1,'Monthly costs'!$B$15,'Monthly costs'!$B$16)/20 -> 419.93302 | G37: =D37+E37+F37 -> 985.89427 | H37: =G37/(1-Inputs!$B$33) -> 1006.0146 | I37: =G37/(1-Inputs!$B$33-Inputs!$B$34) -> 1263.967
A38: =A6 -> T5 combo + 2 movers, 2-bedroom | B38: =MAX(2,CEILING((0.5+0.4*C6+0.25*E6+C38/Inputs!$B$26)*2,1)/2) -> 6 | C38: =Inputs!$B$24*D6+Inputs!$B$25 -> 56 | D38: =C38*IF(B6=1,'Monthly costs'!$B$20,'Monthly costs'!$B$19) -> 342.86 | E38: =MAX(B38,IF(F6>0,Inputs!$B$32,3))*('Monthly costs'!$B$22+F6*'Monthly costs'!$B$21) -> 1119.42 | F38: =IF(B6=1,'Monthly costs'!$B$15,'Monthly costs'!$B$16)/20 -> 419.93302 | G38: =D38+E38+F38 -> 1882.213 | H38: =G38/(1-Inputs!$B$33) -> 1920.6255 | I38: =G38/(1-Inputs!$B$33-Inputs!$B$34) -> 2413.0936

Sheet Rate card test
A1: Proposed rate card (yellow) | B1: Value
A2: Callout fee (R) | B2: 900
A3: Vehicle and driver per billable hour (R) | B3: 100
A4: Crew per mover per hour (R) | B4: 80
A5: Per move km, bakkie alone (R) | B5: 10
A6: Per move km, with trailer (R) | B6: 12
A7: Stairs per floor (R) | B7: 90
A8: Minimum billable hours, no crew | B8: 3
A9: Minimum billable hours, with crew | B9: 4
A11: Job | B11: Billable hours | C11: Price R | D11: Cost at 12 jobs R | E11: Profit R | F11: Margin
A12: ='Job costs'!A2 -> T1 bakkie transport only, student | B12: =MAX(IF('Job costs'!F2>0,$B$9,$B$8),'Job costs'!B18) -> 3 | C12: =$B$2+$B$3*B12+IF('Job costs'!B2=1,$B$6,$B$5)*'Job costs'!D2+$B$4*'Job costs'!F2*B12+$B$7*'Job costs'!E2 -> 1300 | D12: ='Job costs'!G18 -> 998.8905 | E12: =C12*(1-Inputs!$B$33)-D12 -> 275.1095 | F12: =E12/C12 -> 0.21162269
A13: ='Job costs'!A3 -> T2 bakkie + 2 movers, student room | B13: =MAX(IF('Job costs'!F3>0,$B$9,$B$8),'Job costs'!B19) -> 4 | C13: =$B$2+$B$3*B13+IF('Job costs'!B3=1,$B$6,$B$5)*'Job costs'!D3+$B$4*'Job costs'!F3*B13+$B$7*'Job costs'!E3 -> 2040 | D13: ='Job costs'!G19 -> 1511.958 | E13: =C13*(1-Inputs!$B$33)-D13 -> 487.242 | F13: =E13/C13 -> 0.23884412
A14: ='Job costs'!A4 -> T3 combo + 2 movers, 1-bedroom | B14: =MAX(IF('Job costs'!F4>0,$B$9,$B$8),'Job costs'!B20) -> 4.5 | C14: =$B$2+$B$3*B14+IF('Job costs'!B4=1,$B$6,$B$5)*'Job costs'!D4+$B$4*'Job costs'!F4*B14+$B$7*'Job costs'!E4 -> 2490 | D14: ='Job costs'!G20 -> 1784.3534 | E14: =C14*(1-Inputs!$B$33)-D14 -> 655.84663 | F14: =E14/C14 -> 0.26339222
A15: ='Job costs'!A5 -> T4 combo transport only | B15: =MAX(IF('Job costs'!F5>0,$B$9,$B$8),'Job costs'!B21) -> 3.5 | C15: =$B$2+$B$3*B15+IF('Job costs'!B5=1,$B$6,$B$5)*'Job costs'!D5+$B$4*'Job costs'!F5*B15+$B$7*'Job costs'!E5 -> 1550 | D15: ='Job costs'!G21 -> 1265.8496 | E15: =C15*(1-Inputs!$B$33)-D15 -> 253.15038 | F15: =E15/C15 -> 0.16332282
A16: ='Job costs'!A6 -> T5 combo + 2 movers, 2-bedroom | B16: =MAX(IF('Job costs'!F6>0,$B$9,$B$8),'Job costs'!B22) -> 6 | C16: =$B$2+$B$3*B16+IF('Job costs'!B6=1,$B$6,$B$5)*'Job costs'!D6+$B$4*'Job costs'!F6*B16+$B$7*'Job costs'!E6 -> 3090 | D16: ='Job costs'!G22 -> 2162.1684 | E16: =C16*(1-Inputs!$B$33)-D16 -> 866.03163 | F16: =E16/C16 -> 0.28026914
